pkg_eladpt/__init__.py
pkg_eladpt/run.py
example_package_eladpt-0.0.41.dist-info/METADATA
example_package_eladpt-0.0.41.dist-info/WHEEL
example_package_eladpt-0.0.41.dist-info/top_level.txt
example_package_eladpt-0.0.41.dist-info/RECORD
