Metadata-Version: 2.1
Name: example-package-eladpt
Version: 0.0.41
Summary: A small example package
Author-email: Example Author <author@example.com>
Project-URL: Homepage, http://another.com
Project-URL: Bug Tracker, http://sec.com
Keywords: eladpt
Classifier: Programming Language :: Python :: 3
Classifier: Operating System :: OS Independent
Requires-Python: >=3.8
Requires-Dist: requests
